MANIFEST.in
requirements.txt
setup.py
awstools/__init__.py
awstools/_aws.py
awstools/ec2.py
awstools/encryption.py
awstools/events.py
awstools/s3.py
awstools/setup.py
awstools/transcoder.py
awstools/utils.py
awstools/watermark.py
py_awstools.egg-info/PKG-INFO
py_awstools.egg-info/SOURCES.txt
py_awstools.egg-info/dependency_links.txt
py_awstools.egg-info/requires.txt
py_awstools.egg-info/top_level.txt