Metadata-Version: 1.0
Name: py-awstools
Version: 0.1.0
Summary: Simple wrappers for boto3 to make life easier
Home-page: https://github.com/jaredlunde/awstools
Author: Jared Lunde
Author-email: jared.lunde@gmail.com
License: MIT
Platform: UNKNOWN
